LICENSE.txt
README.md
setup.py
R4P/__init__.py
R4P/executor.py
R4P.egg-info/PKG-INFO
R4P.egg-info/SOURCES.txt
R4P.egg-info/dependency_links.txt
R4P.egg-info/top_level.txt