Metadata-Version: 2.1
Name: R4P
Version: 0.1
Summary: A simple library to execute Python code using exec
Classifier: Programming Language :: Python :: 3
Classifier: License :: OSI Approved :: MIT License
Classifier: Operating System :: OS Independent
Requires-Python: >=3.6
License-File: LICENSE.txt
